capylayer/__init__.py
capylayer/__main__.py
capylayer/modules/__init__.py
capylayer/modules/_ahk/capylayer_ahk32.exe
capylayer/modules/_ahk/capylayer_ahk64.exe
capylayer/modules/_darwin_nix_handler.py
capylayer/modules/_win_handler.py
capylayer/modules/data/profiles/dvorak.json
capylayer/modules/data/profiles/text_mov.json
capylayer/modules/data/program_config.json
capylayer/modules/io_utils.py
capylayer/modules/models.py
capylayer/modules/models_handler.py
capylayer-0.1.4.dist-info/entry_points.txt
capylayer-0.1.4.dist-info/LICENSE
capylayer-0.1.4.dist-info/METADATA
capylayer-0.1.4.dist-info/WHEEL
capylayer-0.1.4.dist-info/RECORD
