Metadata-Version: 2.1
Name: capylayer
Version: 0.1.4
Summary: Create key layers to your keyboard
Home-page: https://github.com/figdavi/capylayer
License: MIT
Keywords: keyboard,keyboard-layout,key-layers,remapping-keys
Author: figdavi
Author-email: figueiredodavi@outlook.com
Requires-Python: >=3.12,<4.0
Classifier: License :: OSI Approved :: MIT License
Classifier: Programming Language :: Python :: 3
Classifier: Programming Language :: Python :: 3.12
Classifier: Programming Language :: Python :: 3.13
Requires-Dist: keyboard (>=0.13.5,<0.14.0)
Requires-Dist: pydantic (>=2.10.3,<3.0.0)
Project-URL: Repository, https://github.com/figdavi/capylayer
